{
    "files": [
        "SEGA Mega Drive & Genesis Classics (USA).exe"
    ],
    "steam": {
        "appid": "34270",
        "appurl": "https://store.steampowered.com/app/34270",
        "branchid": "public",
        "builddate": "1591104562",
        "buildid": "5109841",
        "controller_support": "full",
        "installdir": "Sega Classics",
        "keys": [
            "HKEY_CURRENT_USER/SOFTWARE/Sega/SEGA Genesis & Mega Drive Classics"
        ],
        "name": "SEGA Mega Drive & Genesis Classics",
        "paths": [
            "STORE_INSTALL_DIR/userdata/STORE_USER_ID/34270",
            "USER_PROFILE_DIR/Documents/SEGA Genesis Classics",
            "USER_PROFILE_DIR/Documents/SEGA Genesis Classics Collection",
            "USER_PROFILE_DIR/Documents/SEGA Mega Drive Classics"
        ]
    },
    "transform_file": "SEGA Mega Drive & Genesis Classics (USA).exe"
}