{
    "files": [
        "Dead Rising 4 (USA).7z.001",
        "Dead Rising 4 (USA).7z.002",
        "Dead Rising 4 (USA).7z.003",
        "Dead Rising 4 (USA).7z.004",
        "Dead Rising 4 (USA).7z.005",
        "Dead Rising 4 (USA).7z.006",
        "Dead Rising 4 (USA).7z.007",
        "Dead Rising 4 (USA).7z.008",
        "Dead Rising 4 (USA).7z.009",
        "Dead Rising 4 (USA).7z.010",
        "Dead Rising 4 (USA).7z.011",
        "Dead Rising 4 (USA).7z.012",
        "Dead Rising 4 (USA).7z.013",
        "Dead Rising 4 (USA).7z.014",
        "Dead Rising 4 (USA).exe"
    ],
    "installer_exe": [
        "$SETUP_MAIN_ROOT/Dead Rising 4 (USA).exe"
    ],
    "steam": {
        "appid": "543460",
        "branchid": "public",
        "controller_support": "full",
        "name": "Dead Rising 4"
    },
    "transform_file": "Dead Rising 4 (USA).exe"
}