[
    {
        "dir": "Roms/Other/Mattel Intellivision/ABPA Backgammon ~ Backgammon (World)",
        "filename": "ABPA Backgammon ~ Backgammon (World).int",
        "filename_enc": "0abe6337d0887bcbdaacd4e1a893bb10.enc",
        "hash": "e3f914461629bde1",
        "hash_enc": "3946dbf8cbfea31af672095e03f8a136",
        "mtime": 1724027763,
        "size": 8192,
        "size_enc": 8300
    },
    {
        "dir": "Roms/Other/Mattel Intellivision/Advanced Dungeons & Dragons - Cloudy Mountain (World)",
        "filename": "Advanced Dungeons & Dragons - Cloudy Mountain (World).int",
        "filename_enc": "83a2c0d7982c384e35b4d3eadcabeb8c.enc",
        "hash": "ffb2731b36307949",
        "hash_enc": "35e8a832b7a0425b68f2c83f94acfd9d",
        "mtime": 1724014748,
        "size": 16384,
        "size_enc": 16512
    },
    {
        "dir": "Roms/Other/Mattel Intellivision/Armor Battle (USA, Europe)",
        "filename": "Armor Battle (USA, Europe).int",
        "filename_enc": "ce84c1febd16d23a642520b533bd48b2.enc",
        "hash": "f9c9cbb5ddaf4ae5",
        "hash_enc": "ed30d49ca5b7ede0bd9084dc77b22484",
        "mtime": 1724014748,
        "size": 8192,
        "size_enc": 8290
    },
    {
        "dir": "Roms/Other/Mattel Intellivision/Astrosmash (USA, Europe)",
        "filename": "Astrosmash (USA, Europe).int",
        "filename_enc": "5318a4db4f8c0bac1ebb554228b6aa05.enc",
        "hash": "3479dd2cd6f94a82",
        "hash_enc": "b060255db8b93533bd10879ea639796f",
        "mtime": 1724014749,
        "size": 8192,
        "size_enc": 8288
    },
    {
        "dir": "Roms/Other/Mattel Intellivision/Auto Racing (World)",
        "filename": "Auto Racing (World).int",
        "filename_enc": "a8ae80ef1defc125344d2a15ca9ce200.enc",
        "hash": "a25d28304535286f",
        "hash_enc": "a239c222d413e7f83cfce30da22e549b",
        "mtime": 1724014749,
        "size": 8192,
        "size_enc": 8283
    },
    {
        "dir": "Roms/Other/Mattel Intellivision/B-17 Bomber (USA, Europe)",
        "filename": "B-17 Bomber (USA, Europe).int",
        "filename_enc": "a57d71145adbdb668d55c7c065815cf0.enc",
        "hash": "e8340bf4c14270c5",
        "hash_enc": "9d50d9fe84feccec56d378ed87df4399",
        "mtime": 1724014749,
        "size": 24576,
        "size_enc": 24676
    },
    {
        "dir": "Roms/Other/Mattel Intellivision/Body Slam! Super Pro Wrestling (USA)",
        "filename": "Body Slam! Super Pro Wrestling (USA).int",
        "filename_enc": "44878a3fa4ed00599d5df3a85e29b206.enc",
        "hash": "be405574d23c2786",
        "hash_enc": "60bb2c68fff8e2482c2d694584ec4068",
        "mtime": 1724014750,
        "size": 32768,
        "size_enc": 32879
    },
    {
        "dir": "Roms/Other/Mattel Intellivision/Bomb Squad (USA, Europe)",
        "filename": "Bomb Squad (USA, Europe).int",
        "filename_enc": "079f2c997c22235f221734f034507edf.enc",
        "hash": "71309760299e3e21",
        "hash_enc": "d4840221e0d01776c21cbef8c062dba7",
        "mtime": 1724014750,
        "size": 24576,
        "size_enc": 24675
    },
    {
        "dir": "Roms/Other/Mattel Intellivision/Boxing (World)",
        "filename": "Boxing (World).int",
        "filename_enc": "b1f351093aa3dc49a582c5d41346b0a0.enc",
        "hash": "77d9807a02a30f8b",
        "hash_enc": "791187f16bf18cfea2122bd8a405dd50",
        "mtime": 1724014750,
        "size": 8192,
        "size_enc": 8278
    },
    {
        "dir": "Roms/Other/Mattel Intellivision/Brickout! (World)",
        "filename": "Brickout! (World).int",
        "filename_enc": "5db8d7e147490cad67163939dbf99b1b.enc",
        "hash": "65e40e3c7e7692df",
        "hash_enc": "fa44f95bdc247159fd4acc9e6e5b9fc9",
        "mtime": 1724014751,
        "size": 8192,
        "size_enc": 8281
    },
    {
        "dir": "Roms/Other/Mattel Intellivision/Buzz Bombers (USA, Europe)",
        "filename": "Buzz Bombers (USA, Europe).int",
        "filename_enc": "16eeca1514a5ff24082b68b36052ee41.enc",
        "hash": "5d20a1543af9bc66",
        "hash_enc": "f868aadb257405931fa7a675154094a2",
        "mtime": 1724014751,
        "size": 16384,
        "size_enc": 16485
    },
    {
        "dir": "Roms/Other/Mattel Intellivision/Checkers ~ Draughts (USA, Europe)",
        "filename": "Checkers ~ Draughts (USA, Europe).int",
        "filename_enc": "39d2fcf681dc9886be30dff2970d4535.enc",
        "hash": "ada69dae6639ae13",
        "hash_enc": "77ca2f03cd1d60b0467dbcffda3c9e90",
        "mtime": 1724027763,
        "size": 8192,
        "size_enc": 8297
    },
    {
        "dir": "Roms/Other/Mattel Intellivision/Chip Shot - Super Pro Golf (USA)",
        "filename": "Chip Shot - Super Pro Golf (USA).int",
        "filename_enc": "763d6d1408d61f55ba568ba50d11b700.enc",
        "hash": "2b9646ae5b9cb592",
        "hash_enc": "37b15a9649d990890060e1b4554ad60e",
        "mtime": 1724014752,
        "size": 32768,
        "size_enc": 32875
    },
    {
        "dir": "Roms/Other/Mattel Intellivision/Deep Pockets - Super Pro Pool and Billiards (World)",
        "filename": "Deep Pockets - Super Pro Pool and Billiards (World).int",
        "filename_enc": "018568e6104d1dd69ed34c45b92d3a22.enc",
        "hash": "77eaa28f44874ed1",
        "hash_enc": "b8d307f81fb58a890ce4aeec5275b4be",
        "mtime": 1724014752,
        "size": 32768,
        "size_enc": 32894
    },
    {
        "dir": "Roms/Other/Mattel Intellivision/Demo Cartridge (World)",
        "filename": "Demo Cartridge (World).int",
        "filename_enc": "0a9440a7812f012c0224f2411823dc50.enc",
        "hash": "678fdf501bae023e",
        "hash_enc": "5e0996b72917ab21b471531c9f0ee6b6",
        "mtime": 1724014752,
        "size": 16384,
        "size_enc": 16481
    },
    {
        "dir": "Roms/Other/Mattel Intellivision/Electric Company, The - Math Fun (USA, Europe)",
        "filename": "Electric Company, The - Math Fun (USA, Europe).int",
        "filename_enc": "dd306ac9977dcccb8e15d9ffe4ace5aa.enc",
        "hash": "b068ce15deeeadc5",
        "hash_enc": "75121b77db9a458b3a148b374c96a7fd",
        "mtime": 1724014753,
        "size": 8192,
        "size_enc": 8310
    },
    {
        "dir": "Roms/Other/Mattel Intellivision/Electric Company, The - Word Fun (USA, Europe)",
        "filename": "Electric Company, The - Word Fun (USA, Europe).int",
        "filename_enc": "b7d31ba7905a728e6f938fa0a8bd990b.enc",
        "hash": "af337b97763f3b03",
        "hash_enc": "fa33090019c58385bf804dfdab8f9c1f",
        "mtime": 1724014753,
        "size": 8192,
        "size_enc": 8310
    },
    {
        "dir": "Roms/Other/Mattel Intellivision/Frog Bog (World)",
        "filename": "Frog Bog (World).int",
        "filename_enc": "c0d9703f1f4ede1d6a03763f7fff2156.enc",
        "hash": "d26f668d888c966b",
        "hash_enc": "208d8f72308fc12f00921baf1c7ac7d4",
        "mtime": 1724014753,
        "size": 8192,
        "size_enc": 8280
    },
    {
        "dir": "Roms/Other/Mattel Intellivision/Hard Hat (World)",
        "filename": "Hard Hat (World).int",
        "filename_enc": "556000653402080b3f52c84cd3fcddd7.enc",
        "hash": "66d5ce2eb155527f",
        "hash_enc": "98772b3c635b522b0033244fe0497a76",
        "mtime": 1724014754,
        "size": 16384,
        "size_enc": 16475
    },
    {
        "dir": "Roms/Other/Mattel Intellivision/Horse Racing (World)",
        "filename": "Horse Racing (World).int",
        "filename_enc": "89ec6dce0c87af4b11ff5893b9d15097.enc",
        "hash": "872603589f7c42e0",
        "hash_enc": "f3b65d3aa14532dec3550455e24740e2",
        "mtime": 1724014754,
        "size": 8192,
        "size_enc": 8284
    },
    {
        "dir": "Roms/Other/Mattel Intellivision/Hover Force (USA)",
        "filename": "Hover Force (USA).int",
        "filename_enc": "88d87798827f5e5f1471b35d747ec210.enc",
        "hash": "519742c176abc396",
        "hash_enc": "694b1ac76c6aa1eda0dd893c1a27b820",
        "mtime": 1724014754,
        "size": 49152,
        "size_enc": 49244
    },
    {
        "dir": "Roms/Other/Mattel Intellivision/Hypnotic Lights (World)",
        "filename": "Hypnotic Lights (World).int",
        "filename_enc": "7f6af7ad194d91fa35dfc4c1e55a6766.enc",
        "hash": "0a80faf710de465b",
        "hash_enc": "4f36817be652db144afef74869e0f8fa",
        "mtime": 1724014755,
        "size": 8192,
        "size_enc": 8287
    },
    {
        "dir": "Roms/Other/Mattel Intellivision/King of the Mountain (USA) (Proto)",
        "filename": "King of the Mountain (USA) (Proto).int",
        "filename_enc": "b960fa8df79138840896f50acbcf2a63.enc",
        "hash": "a97a9bc0b6bf9fab",
        "hash_enc": "f1f64ccf700641d534443bf7ad863a33",
        "mtime": 1724014755,
        "size": 32768,
        "size_enc": 32877
    },
    {
        "dir": "Roms/Other/Mattel Intellivision/Land Battle (USA) (Proto)",
        "filename": "Land Battle (USA) (Proto).int",
        "filename_enc": "95a6274014118f26b69c4356cc1361d3.enc",
        "hash": "266b5252587ae859",
        "hash_enc": "cde9d4e477647428118e21b5b5c72398",
        "mtime": 1724014755,
        "size": 16384,
        "size_enc": 16484
    },
    {
        "dir": "Roms/Other/Mattel Intellivision/Las Vegas Poker & Blackjack ~ Blackjack & Poker (World)",
        "filename": "Las Vegas Poker & Blackjack ~ Blackjack & Poker (World).int",
        "filename_enc": "cc41c70165e77c4e4bdf23bc655adacf.enc",
        "hash": "b7902db650c80e2a",
        "hash_enc": "59c0f800371439a7371984c7c4dae1f3",
        "mtime": 1724027763,
        "size": 8192,
        "size_enc": 8319
    },
    {
        "dir": "Roms/Other/Mattel Intellivision/Las Vegas Roulette (World)",
        "filename": "Las Vegas Roulette (World).int",
        "filename_enc": "1a9f018faaa08434cbd5c4684d77631b.enc",
        "hash": "a4fabb2c24d2c458",
        "hash_enc": "a32f3bdad13b1cfdf3799c668cd9be15",
        "mtime": 1724014756,
        "size": 8192,
        "size_enc": 8290
    },
    {
        "dir": "Roms/Other/Mattel Intellivision/Learning Fun I - Math Master, Factor Fun (USA)",
        "filename": "Learning Fun I - Math Master, Factor Fun (USA).int",
        "filename_enc": "5f7d385d34119d1516efec2954f3f0a9.enc",
        "hash": "0d21a1e4d3787b2c",
        "hash_enc": "aa8bdee6856dab5294c3381baaabeffe",
        "mtime": 1724014756,
        "size": 16384,
        "size_enc": 16505
    },
    {
        "dir": "Roms/Other/Mattel Intellivision/Learning Fun II - Word Wizard, Memory Fun (USA)",
        "filename": "Learning Fun II - Word Wizard, Memory Fun (USA).int",
        "filename_enc": "c6de9da6ff15fae8c6846fd452014eb3.enc",
        "hash": "d36cf765f2a69a4c",
        "hash_enc": "d35c98a3c524c75b2a17e0d315ed0d24",
        "mtime": 1724014757,
        "size": 16384,
        "size_enc": 16506
    },
    {
        "dir": "Roms/Other/Mattel Intellivision/Magic Carousel (USA) (Proto)",
        "filename": "Magic Carousel (USA) (Proto).int",
        "filename_enc": "35743e65cb4f7c180a55da75d442d119.enc",
        "hash": "acfc0ad284844aec",
        "hash_enc": "82c714a1d7805e1caf3b865629fcd761",
        "mtime": 1724014757,
        "size": 32768,
        "size_enc": 32871
    },
    {
        "dir": "Roms/Other/Mattel Intellivision/Major League Baseball ~ Big League Baseball ~ Baseball (World)",
        "filename": "Major League Baseball ~ Big League Baseball ~ Baseball (World).int",
        "filename_enc": "32891248fc43e9ef2ec141e332d13b74.enc",
        "hash": "eba0e4b576564613",
        "hash_enc": "500ad343d96703b31eae05c5ea34ecd0",
        "mtime": 1724027764,
        "size": 8192,
        "size_enc": 8326
    },
    {
        "dir": "Roms/Other/Mattel Intellivision/Mind Strike (USA, Europe)",
        "filename": "Mind Strike (USA, Europe).int",
        "filename_enc": "53a23c938eb47b448fbf4cb865687a69.enc",
        "hash": "b97a16c28ec0e5a6",
        "hash_enc": "a217c1237ba5969a190e40c3cf123252",
        "mtime": 1724014758,
        "size": 24576,
        "size_enc": 24676
    },
    {
        "dir": "Roms/Other/Mattel Intellivision/Motocross (USA)",
        "filename": "Motocross (USA).int",
        "filename_enc": "7b851e71522bcb6391022d1757cc88f6.enc",
        "hash": "11b05eac83456973",
        "hash_enc": "9b44f24c6697d30b114016acae3bb19c",
        "mtime": 1724014758,
        "size": 16384,
        "size_enc": 16474
    },
    {
        "dir": "Roms/Other/Mattel Intellivision/Mountain Madness - Super Pro Skiing (USA)",
        "filename": "Mountain Madness - Super Pro Skiing (USA).int",
        "filename_enc": "73b24306009e9eeebc26f6c172c8d89c.enc",
        "hash": "d78d4645e8a02ace",
        "hash_enc": "e83ce44d82c438d1a9442ea05c72b3c9",
        "mtime": 1724014758,
        "size": 16384,
        "size_enc": 16500
    },
    {
        "dir": "Roms/Other/Mattel Intellivision/NASL Soccer ~ Soccer (World)",
        "filename": "NASL Soccer ~ Soccer (World).int",
        "filename_enc": "8cc1208c38552f4792393ec665d617fb.enc",
        "hash": "03888c7e835fe036",
        "hash_enc": "bd7e5bc1b50efbe0b363db53166e5bd6",
        "mtime": 1724027764,
        "size": 8192,
        "size_enc": 8292
    },
    {
        "dir": "Roms/Other/Mattel Intellivision/NBA Basketball ~ Basketball (USA, Europe)",
        "filename": "NBA Basketball ~ Basketball (USA, Europe).int",
        "filename_enc": "a81fdbf304ec487e8ea89f7302967d91.enc",
        "hash": "e3be45280e069332",
        "hash_enc": "ee725735a41c2ffe467f94798a8b6d4d",
        "mtime": 1724027764,
        "size": 8192,
        "size_enc": 8305
    },
    {
        "dir": "Roms/Other/Mattel Intellivision/NFL Football ~ Football (World)",
        "filename": "NFL Football ~ Football (World).int",
        "filename_enc": "0a35700b8ef337ed4e8b1c0727b48d6a.enc",
        "hash": "80c8c4f40c61cc56",
        "hash_enc": "8d52a4a3bdefb2c576020992d6bf0102",
        "mtime": 1724027765,
        "size": 8192,
        "size_enc": 8295
    },
    {
        "dir": "Roms/Other/Mattel Intellivision/NHL Hockey ~ Hockey (World)",
        "filename": "NHL Hockey ~ Hockey (World).int",
        "filename_enc": "1e9d3ad141d575f95423cc3bbe5d58f0.enc",
        "hash": "2471dba08645ff2b",
        "hash_enc": "e08709712521b7c19f826a4bccd20948",
        "mtime": 1724027765,
        "size": 8192,
        "size_enc": 8291
    },
    {
        "dir": "Roms/Other/Mattel Intellivision/Night Stalker (World)",
        "filename": "Night Stalker (World).int",
        "filename_enc": "d43c58f5402ede93cfd45fa901892dd8.enc",
        "hash": "87a53bb1c25e5da2",
        "hash_enc": "ffb5ba4be0e80545bcde9a9e892b6bc7",
        "mtime": 1724014760,
        "size": 8192,
        "size_enc": 8285
    },
    {
        "dir": "Roms/Other/Mattel Intellivision/Number Jumble (USA) (Proto)",
        "filename": "Number Jumble (USA) (Proto).int",
        "filename_enc": "8a5260d15f3dea5da89deca93bcc89b8.enc",
        "hash": "246c50259fd44754",
        "hash_enc": "91281c128e78837b0e050d0854a09366",
        "mtime": 1724014760,
        "size": 32768,
        "size_enc": 32870
    },
    {
        "dir": "Roms/Other/Mattel Intellivision/PBA Bowling ~ Bowling (World)",
        "filename": "PBA Bowling ~ Bowling (World).int",
        "filename_enc": "f06416431fc82b1cfc76c22d537c21c6.enc",
        "hash": "827f6d24cf821597",
        "hash_enc": "f7b13d6bdeb5a85df7fc7baae181afea",
        "mtime": 1724027765,
        "size": 8192,
        "size_enc": 8293
    },
    {
        "dir": "Roms/Other/Mattel Intellivision/PGA Golf ~ Golf (World)",
        "filename": "PGA Golf ~ Golf (World).int",
        "filename_enc": "d3ef45a58b500982c5d152c53693f124.enc",
        "hash": "5789889f50be4d4e",
        "hash_enc": "f7186b076de567c8886ebf8ba5339cb6",
        "mtime": 1724027766,
        "size": 8192,
        "size_enc": 8287
    },
    {
        "dir": "Roms/Other/Mattel Intellivision/Party Line - Space Cadet (USA) (Proto)",
        "filename": "Party Line - Space Cadet (USA) (Proto).int",
        "filename_enc": "21046047acc42703c78a57fb3579aa61.enc",
        "hash": "e4a9583f1f0da13b",
        "hash_enc": "1cc5d537a284cf10082018cb677fbb8c",
        "mtime": 1724014761,
        "size": 16384,
        "size_enc": 16497
    },
    {
        "dir": "Roms/Other/Mattel Intellivision/Pinball (USA)",
        "filename": "Pinball (USA).int",
        "filename_enc": "115fe936b23160a2e416ce6a8bb5560d.enc",
        "hash": "1afdd2b1a1341d05",
        "hash_enc": "d2e6ec8cbeeb6de6aaadd2c153328010",
        "mtime": 1724014762,
        "size": 24576,
        "size_enc": 24664
    },
    {
        "dir": "Roms/Other/Mattel Intellivision/Reversi (USA, Europe)",
        "filename": "Reversi (USA, Europe).int",
        "filename_enc": "eb4675a8ec03ca2dcd8d31a16751b021.enc",
        "hash": "dd0086f2a98b208f",
        "hash_enc": "7d4be65f65761cccb06a36c59d0bad48",
        "mtime": 1724014762,
        "size": 8192,
        "size_enc": 8285
    },
    {
        "dir": "Roms/Other/Mattel Intellivision/Royal Dealer (USA, Europe)",
        "filename": "Royal Dealer (USA, Europe).int",
        "filename_enc": "d3ea4d9d9d9ef0d87eaf88dbbc5ae4c8.enc",
        "hash": "2e91dd8820c72159",
        "hash_enc": "8c315c0879ce4b4c108c03bf9193dbed",
        "mtime": 1724014762,
        "size": 16384,
        "size_enc": 16485
    },
    {
        "dir": "Roms/Other/Mattel Intellivision/SNAFU (World)",
        "filename": "SNAFU (World).int",
        "filename_enc": "44525bc069d2ac72e9d33faccb4b652f.enc",
        "hash": "23f4d3b750d74392",
        "hash_enc": "8dacacd56bde49090197aec9263b3793",
        "mtime": 1724014763,
        "size": 8192,
        "size_enc": 8277
    },
    {
        "dir": "Roms/Other/Mattel Intellivision/Sea Battle (World)",
        "filename": "Sea Battle (World).int",
        "filename_enc": "22a69b457423e8ee0273f626e9d59d7c.enc",
        "hash": "b51626ebc11463a5",
        "hash_enc": "3fa939c4241378c1f95e3a33b5ba965b",
        "mtime": 1724014763,
        "size": 8192,
        "size_enc": 8282
    },
    {
        "dir": "Roms/Other/Mattel Intellivision/Shark! Shark! (USA, Europe)",
        "filename": "Shark! Shark! (USA, Europe).int",
        "filename_enc": "b17c2e751d9f2cd168418d633fea1c69.enc",
        "hash": "0daab88711409985",
        "hash_enc": "895e3c6240eaf46db2f6e9e3f7dc6b85",
        "mtime": 1724014764,
        "size": 16384,
        "size_enc": 16486
    },
    {
        "dir": "Roms/Other/Mattel Intellivision/Sharp Shot (USA, Europe)",
        "filename": "Sharp Shot (USA, Europe).int",
        "filename_enc": "8a72eb505566feb6d4c57e2cec640849.enc",
        "hash": "25b90652ad5b073f",
        "hash_enc": "452ba1eb0e1a2002c05a8556734e2814",
        "mtime": 1724014764,
        "size": 8192,
        "size_enc": 8288
    },
    {
        "dir": "Roms/Other/Mattel Intellivision/Slam Dunk - Super Pro Basketball (USA)",
        "filename": "Slam Dunk - Super Pro Basketball (USA).int",
        "filename_enc": "b386b5c8a9dd6dd0ffbe04b19d9d6957.enc",
        "hash": "247bdaaa5b798ccd",
        "hash_enc": "0911e2839bcf6d3aaad6709100b480de",
        "mtime": 1724014764,
        "size": 32768,
        "size_enc": 32881
    },
    {
        "dir": "Roms/Other/Mattel Intellivision/Slap Shot - Super Pro Hockey (USA)",
        "filename": "Slap Shot - Super Pro Hockey (USA).int",
        "filename_enc": "6d8360c0c8aba0f73b5c0e11659c248f.enc",
        "hash": "215e661a564bf0c5",
        "hash_enc": "4b07ae59b80452d33774b16a0e4ce8d5",
        "mtime": 1724014765,
        "size": 16384,
        "size_enc": 16493
    },
    {
        "dir": "Roms/Other/Mattel Intellivision/Space Armada (World)",
        "filename": "Space Armada (World).int",
        "filename_enc": "2ca16546fab55c0f202d5c770769c2d7.enc",
        "hash": "974908fff7a56b3e",
        "hash_enc": "b8af07bbfdf84a0aefd690c796028737",
        "mtime": 1724014765,
        "size": 8192,
        "size_enc": 8284
    },
    {
        "dir": "Roms/Other/Mattel Intellivision/Space Battle (World)",
        "filename": "Space Battle (World).int",
        "filename_enc": "8de5c43b970fd69a603c382d309b9a0e.enc",
        "hash": "f68becae6f9f123f",
        "hash_enc": "93fd5215241145e80a6f75977d98ae63",
        "mtime": 1724014765,
        "size": 8192,
        "size_enc": 8284
    },
    {
        "dir": "Roms/Other/Mattel Intellivision/Space Hawk (USA, Europe)",
        "filename": "Space Hawk (USA, Europe).int",
        "filename_enc": "3beeb4d37a6cd7253a9342acb72ca700.enc",
        "hash": "447122e52dff2c95",
        "hash_enc": "9523690b769cc367134b6cbc793b1359",
        "mtime": 1724014766,
        "size": 8192,
        "size_enc": 8288
    },
    {
        "dir": "Roms/Other/Mattel Intellivision/Space Spartans (USA, Europe)",
        "filename": "Space Spartans (USA, Europe).int",
        "filename_enc": "2a8f76fe5f8579bb4226ef1904a495ab.enc",
        "hash": "cf9a7bf84f30dd91",
        "hash_enc": "69d1c96ca4e72b78c388fa5dfc6691e2",
        "mtime": 1724014766,
        "size": 16384,
        "size_enc": 16487
    },
    {
        "dir": "Roms/Other/Mattel Intellivision/Spiker - Super Pro Volleyball (USA)",
        "filename": "Spiker - Super Pro Volleyball (USA).int",
        "filename_enc": "36550d46aa83522ad16b763cf9a149a4.enc",
        "hash": "ae3cd895f4e1a6e5",
        "hash_enc": "4e25b9953b7898da439817c4d023bf03",
        "mtime": 1724014766,
        "size": 32768,
        "size_enc": 32878
    },
    {
        "dir": "Roms/Other/Mattel Intellivision/Stadium Mud Buggies (USA)",
        "filename": "Stadium Mud Buggies (USA).int",
        "filename_enc": "05ff8fb3bb231e6dc921b72c22d4ff50.enc",
        "hash": "08ae1948a24ad383",
        "hash_enc": "8a21449b1987a8c4f98cb385289135b1",
        "mtime": 1724014767,
        "size": 32768,
        "size_enc": 32868
    },
    {
        "dir": "Roms/Other/Mattel Intellivision/Star Strike (World)",
        "filename": "Star Strike (World).int",
        "filename_enc": "4463a7cae0fffe45682509fb04229bcc.enc",
        "hash": "360f16ee85639776",
        "hash_enc": "e17611e15279ed8f31c3450dcaa21884",
        "mtime": 1724014767,
        "size": 8192,
        "size_enc": 8283
    },
    {
        "dir": "Roms/Other/Mattel Intellivision/Sub Hunt (USA, Europe)",
        "filename": "Sub Hunt (USA, Europe).int",
        "filename_enc": "8b035f9fae6da09621ddb4339d124bf1.enc",
        "hash": "fd3994746883dc0d",
        "hash_enc": "83f9c5b7efbaf4329b810d3fa4381efa",
        "mtime": 1724014767,
        "size": 16384,
        "size_enc": 16481
    },
    {
        "dir": "Roms/Other/Mattel Intellivision/Super Pro Decathlon (USA)",
        "filename": "Super Pro Decathlon (USA).int",
        "filename_enc": "4e11500d72a084f32613dd2f39593444.enc",
        "hash": "2ce1659be42ce56b",
        "hash_enc": "f052980800d0fab3cc69db8fe9634f95",
        "mtime": 1724014768,
        "size": 32768,
        "size_enc": 32868
    },
    {
        "dir": "Roms/Other/Mattel Intellivision/Super Pro Football (USA)",
        "filename": "Super Pro Football (USA).int",
        "filename_enc": "cfdd6b0cbdb41ac410004e2223bba683.enc",
        "hash": "5cb97a652b77b013",
        "hash_enc": "b3b510a17daa8e2592a5b4e9fe71fcda",
        "mtime": 1724014768,
        "size": 32768,
        "size_enc": 32867
    },
    {
        "dir": "Roms/Other/Mattel Intellivision/Super Soccer (USA) (Proto)",
        "filename": "Super Soccer (USA) (Proto).int",
        "filename_enc": "12fa23d9edcdb39a3adeac5f6aef40ee.enc",
        "hash": "a72f0f1cfcca58cd",
        "hash_enc": "4bbb0349c5b7701159caa3836bbe1590",
        "mtime": 1724014768,
        "size": 32768,
        "size_enc": 32869
    },
    {
        "dir": "Roms/Other/Mattel Intellivision/Takeover (USA) (Proto)",
        "filename": "Takeover (USA) (Proto).int",
        "filename_enc": "0345bb66e4aeeccb6c200b7970c2b882.enc",
        "hash": "1a95b559ef8a805b",
        "hash_enc": "71217be8304211c2b735f70bc8d64ffc",
        "mtime": 1724014769,
        "size": 8192,
        "size_enc": 8286
    },
    {
        "dir": "Roms/Other/Mattel Intellivision/Tennis (World)",
        "filename": "Tennis (World).int",
        "filename_enc": "64f3d59f8034097bcba82800c70bab0c.enc",
        "hash": "4a3a86525d918ab9",
        "hash_enc": "94b0fd11d00166b46ca7ea36bb12a9ac",
        "mtime": 1724014769,
        "size": 8192,
        "size_enc": 8278
    },
    {
        "dir": "Roms/Other/Mattel Intellivision/Thin Ice (USA) (Beta)",
        "filename": "Thin Ice (USA) (Beta).int",
        "filename_enc": "7ce4f4666ea93699246beab05d4e3c41.enc",
        "hash": "f10e75b2978dcf9c",
        "hash_enc": "84519b05d5d16728a6cc89f9a3b9c6f9",
        "mtime": 1724014769,
        "size": 32768,
        "size_enc": 32864
    },
    {
        "dir": "Roms/Other/Mattel Intellivision/Thunder Castle (USA)",
        "filename": "Thunder Castle (USA).int",
        "filename_enc": "b57128a238406fad32dcc5a61a9c47c5.enc",
        "hash": "f31088cdfa0ea634",
        "hash_enc": "88b0c6d6ef7119417265395418eb0024",
        "mtime": 1724014770,
        "size": 32768,
        "size_enc": 32863
    },
    {
        "dir": "Roms/Other/Mattel Intellivision/Tower of Doom (USA)",
        "filename": "Tower of Doom (USA).int",
        "filename_enc": "7be4606c9bddadb5a2cbb176a5a0f27f.enc",
        "hash": "eb63d77c1af917c1",
        "hash_enc": "bed50ae7640005ee4097fcd7ce551f20",
        "mtime": 1724014770,
        "size": 49152,
        "size_enc": 49246
    },
    {
        "dir": "Roms/Other/Mattel Intellivision/Triple Action (World)",
        "filename": "Triple Action (World).int",
        "filename_enc": "9b42c8614e41f4b53d2d53a37b50ea49.enc",
        "hash": "66bd3d4efc0ff269",
        "hash_enc": "2d42699de54d041d2839e9637a894cd1",
        "mtime": 1724014770,
        "size": 8192,
        "size_enc": 8285
    },
    {
        "dir": "Roms/Other/Mattel Intellivision/US Ski Team Skiing ~ Skiing (World)",
        "filename": "US Ski Team Skiing ~ Skiing (World).int",
        "filename_enc": "53351d84ff7d485cad29d4ced3ba5dff.enc",
        "hash": "63dd351c584c4113",
        "hash_enc": "96fcd69d73b4ff563d53301e35379fe8",
        "mtime": 1724027766,
        "size": 8192,
        "size_enc": 8299
    },
    {
        "dir": "Roms/Other/Mattel Intellivision/USCF Chess ~ Chess (USA, Europe)",
        "filename": "USCF Chess ~ Chess (USA, Europe).int",
        "filename_enc": "13ff58929b99d01a933a960e7cf9a892.enc",
        "hash": "38f1ec6ce7bad19b",
        "hash_enc": "7ab8f89488a42b96c9f4f0bbf5c846e4",
        "mtime": 1724027766,
        "size": 16384,
        "size_enc": 16491
    },
    {
        "dir": "Roms/Other/Mattel Intellivision/Utopia (USA, Europe)",
        "filename": "Utopia (USA, Europe).int",
        "filename_enc": "057409fff0a115be7143b20177ce6f2a.enc",
        "hash": "0eecdab51abab2a9",
        "hash_enc": "b571b23dc74553a5600c35958d72855a",
        "mtime": 1724014771,
        "size": 8192,
        "size_enc": 8284
    },
    {
        "dir": "Roms/Other/Mattel Intellivision/Vectron (USA, Europe)",
        "filename": "Vectron (USA, Europe).int",
        "filename_enc": "558a672f3e807ca61b640fe2e035fd21.enc",
        "hash": "52ef83bc714f5997",
        "hash_enc": "b4c0f80b2511ec142de1c5f9ed18ce6f",
        "mtime": 1724014772,
        "size": 24576,
        "size_enc": 24672
    },
    {
        "dir": "Roms/Other/Mattel Intellivision/World Championship Baseball (USA)",
        "filename": "World Championship Baseball (USA).int",
        "filename_enc": "9fbb5cf1d031c06e30176d660a074f63.enc",
        "hash": "1621eb8c0b88ea37",
        "hash_enc": "087662ad82e76182bf76dcd1fc473d98",
        "mtime": 1724014772,
        "size": 24576,
        "size_enc": 24684
    },
    {
        "dir": "Roms/Other/Mattel Intellivision/World Series Major League Baseball (USA)",
        "filename": "World Series Major League Baseball (USA).int",
        "filename_enc": "db44bf11dfc0d52419e38563120cfacc.enc",
        "hash": "3c19fc73512561bf",
        "hash_enc": "a9c7b60d8920fe7d46feefae42b5fbdb",
        "mtime": 1724014772,
        "size": 49152,
        "size_enc": 49267
    }
]