[
    {
        "dir": "Roms/Other/NEC TurboGrafx CD/Cosmic Fantasy II (USA)",
        "filename": "Cosmic Fantasy II (USA).chd",
        "filename_enc": "20303e7d40f9ef64de9f9f32a2598024.enc",
        "hash": "1cc11c0a4c3e84c7",
        "hash_enc": "3c8bae073dd631638798d32542b126a2",
        "mtime": 1746596165,
        "size": 243056070,
        "size_enc": 243056170
    },
    {
        "dir": "Roms/Other/NEC TurboGrafx CD/Lords of Thunder (USA)",
        "filename": "Lords of Thunder (USA).chd",
        "filename_enc": "f49eaf5258f1e802d903caabc64f625b.enc",
        "hash": "f6cad49fbfc7707c",
        "hash_enc": "57efde5b129e8cb6fbc994cdb1010144",
        "mtime": 1746596242,
        "size": 381018383,
        "size_enc": 381018482
    },
    {
        "dir": "Roms/Other/NEC TurboGrafx CD/Valis II (USA)",
        "filename": "Valis II (USA).chd",
        "filename_enc": "619edbade6f0a60a4855fe701ca6b6f4.enc",
        "hash": "2b282a5c86170b77",
        "hash_enc": "c9e63c476ceef1511a67c43f5ade0510",
        "mtime": 1746596330,
        "size": 278222433,
        "size_enc": 278222524
    },
    {
        "dir": "Roms/Other/NEC TurboGrafx CD/Valis III (USA)",
        "filename": "Valis III (USA).chd",
        "filename_enc": "bdc0b3fccb686ad201b69a25f62a045b.enc",
        "hash": "8fbed5ee54d81c9d",
        "hash_enc": "f6406a66e709ba270e4e8cba33a2d3da",
        "mtime": 1746596400,
        "size": 245335491,
        "size_enc": 245335583
    },
    {
        "dir": "Roms/Other/NEC TurboGrafx CD/Ys Book I & II (USA) (Rev 2)",
        "filename": "Ys Book I & II (USA) (Rev 2).chd",
        "filename_enc": "8d136bb0f6da4b9882fa65f0603b95ce.enc",
        "hash": "b297138c62d2f13e",
        "hash_enc": "72959088ea99072da9b47d56fcc51c61",
        "mtime": 1746596465,
        "size": 477501839,
        "size_enc": 477501944
    }
]