{
    "files": [
        "Fallout 4 VR (USA).7z.001",
        "Fallout 4 VR (USA).7z.002",
        "Fallout 4 VR (USA).7z.003",
        "Fallout 4 VR (USA).7z.004",
        "Fallout 4 VR (USA).7z.005",
        "Fallout 4 VR (USA).7z.006",
        "Fallout 4 VR (USA).exe"
    ],
    "installer_exe": [
        "$SETUP_MAIN_ROOT/Fallout 4 VR (USA).exe"
    ],
    "steam": {
        "appid": "611660",
        "branchid": "public",
        "name": "Fallout 4 VR"
    },
    "transform_file": "Fallout 4 VR (USA).exe"
}