{
    "files": [
        "Crimsonland (USA).exe"
    ],
    "installer_exe": [
        "$SETUP_MAIN_ROOT/Crimsonland (USA).exe"
    ],
    "main_game_exe": [
        "Crimsonland/Crimsonland.exe"
    ],
    "main_game_exe_cwd": {
        "Crimsonland/Crimsonland.exe": "Crimsonland"
    },
    "steam": {
        "appid": "262830",
        "branchid": "public",
        "builddate": "1669037307",
        "buildid": "9959747",
        "controller_support": "full",
        "installdir": "Crimsonland",
        "name": "Crimsonland",
        "paths": [
            "USERPROFILE/AppData/Roaming/10tons/Crimsonland/profiles"
        ]
    },
    "transform_file": "Crimsonland (USA).exe"
}