{
    "files": [
        "Fallout 4 (USA).7z.001",
        "Fallout 4 (USA).7z.002",
        "Fallout 4 (USA).7z.003",
        "Fallout 4 (USA).7z.004",
        "Fallout 4 (USA).7z.005",
        "Fallout 4 (USA).7z.006",
        "Fallout 4 (USA).7z.007",
        "Fallout 4 (USA).7z.008",
        "Fallout 4 (USA).7z.009",
        "Fallout 4 (USA).7z.010",
        "Fallout 4 (USA).7z.011",
        "Fallout 4 (USA).7z.012",
        "Fallout 4 (USA).7z.013",
        "Fallout 4 (USA).7z.014",
        "Fallout 4 (USA).7z.015",
        "Fallout 4 (USA).7z.016",
        "Fallout 4 (USA).7z.017",
        "Fallout 4 (USA).7z.018",
        "Fallout 4 (USA).7z.019",
        "Fallout 4 (USA).7z.020",
        "Fallout 4 (USA).7z.021",
        "Fallout 4 (USA).7z.022",
        "Fallout 4 (USA).exe"
    ],
    "installer_exe": [
        "SETUP_MAIN_ROOT/Fallout 4 (USA).exe"
    ],
    "steam": {
        "appid": "377160",
        "branchid": "public",
        "controller_support": "full",
        "name": "Fallout 4"
    },
    "transform_file": "Fallout 4 (USA).exe"
}