{
    "disc": {
        "appid": "0ea81b06-0e61-4369-acae-db4604220034",
        "appname": "dungeon_keeper_2",
        "installdir": "Dungeon Keeper 2",
        "keys": [],
        "launch": [],
        "name": "Dungeon Keeper 2",
        "paths": [
            "GAME_INSTALL_DIR/Data/Save",
            "GAME_INSTALL_DIR/Data/Settings"
        ],
        "setup": {
            "install": [
                {
                    "cwd": "DISC_MAIN_ROOT",
                    "exe": "Autorun.exe"
                },
                {
                    "cwd": "DISC_UPDATE_ROOT",
                    "exe": "DKII_173.exe"
                }
            ]
        }
    },
    "files": [
        "Dungeon Keeper 2 (USA) (Update).chd",
        "Dungeon Keeper 2 (USA).chd",
        "Dungeon Keeper 2 (USA).m3u"
    ],
    "transform_file": "Dungeon Keeper 2 (USA).m3u"
}