{
    "disc": {
        "appid": "387e9689-7de5-4935-870e-f88b97b9f912",
        "appname": "armello",
        "buildid": "1.0",
        "keys": [
            "HKEY_CURRENT_USER/Software/League of Geeks/Armello"
        ],
        "launch": [],
        "name": "Armello",
        "paths": [
            "USER_PROFILE_DIR/AppData/LocalLow/League of Geeks/Armello"
        ],
        "setup": {
            "install": [
                {
                    "cwd": "DISC_MAIN_ROOT",
                    "exe": "Armello-1.0-windows-installer.exe"
                }
            ]
        }
    },
    "files": [
        "Armello (USA).chd"
    ],
    "transform_file": "Armello (USA).chd"
}