[
    {
        "dir": "Roms/Nintendo/Nintendo Gamecube/007 - Agent Under Fire (USA)",
        "filename": "007 - Agent Under Fire (USA).rvz",
        "hash": "56e2c3d9a9794033",
        "size": "1202704212",
        "mtime": "1599530357"
    },
    {
        "dir": "Roms/Nintendo/Nintendo Gamecube/Chibi-Robo! Plug into Adventure! (USA)",
        "filename": "Chibi-Robo! Plug into Adventure! (USA).rvz",
        "hash": "9c39b12962a877ca",
        "size": "350652488",
        "mtime": "1599529483"
    },
    {
        "dir": "Roms/Nintendo/Nintendo Gamecube/Darkened Skye (USA)",
        "filename": "Darkened Skye (USA).rvz",
        "hash": "f6d692c5b7cf9a2b",
        "size": "1102794696",
        "mtime": "1599529524"
    },
    {
        "dir": "Roms/Nintendo/Nintendo Gamecube/Donkey Kong Jungle Beat (USA)",
        "filename": "Donkey Kong Jungle Beat (USA).rvz",
        "hash": "fce9b5f1bd48afa0",
        "size": "584466460",
        "mtime": "1599529633"
    },
    {
        "dir": "Roms/Nintendo/Nintendo Gamecube/Eternal Darkness - Sanity's Requiem (USA)",
        "filename": "Eternal Darkness - Sanity's Requiem (USA).rvz",
        "hash": "e3f5267e63e46da6",
        "size": "1367830952",
        "mtime": "1599529773"
    },
    {
        "dir": "Roms/Nintendo/Nintendo Gamecube/Final Fantasy - Crystal Chronicles (USA)",
        "filename": "Final Fantasy - Crystal Chronicles (USA).rvz",
        "hash": "f6653ac1a28290eb",
        "size": "834769696",
        "mtime": "1599529887"
    },
    {
        "dir": "Roms/Nintendo/Nintendo Gamecube/Geist (USA)",
        "filename": "Geist (USA).rvz",
        "hash": "00fb33dcda682168",
        "size": "805912176",
        "mtime": "1599530079"
    },
    {
        "dir": "Roms/Nintendo/Nintendo Gamecube/Legend of Zelda, The - Collector's Edition (USA)",
        "filename": "Legend of Zelda, The - Collector's Edition (USA).rvz",
        "hash": "fcee79a488fa7416",
        "size": "947457584",
        "mtime": "1599532587"
    },
    {
        "dir": "Roms/Nintendo/Nintendo Gamecube/Legend of Zelda, The - Four Swords Adventures (USA)",
        "filename": "Legend of Zelda, The - Four Swords Adventures (USA).rvz",
        "hash": "05e4b519bd92c1fc",
        "size": "237857692",
        "mtime": "1599532608"
    },
    {
        "dir": "Roms/Nintendo/Nintendo Gamecube/Legend of Zelda, The - Ocarina of Time & Master Quest (USA)",
        "filename": "Legend of Zelda, The - Ocarina of Time & Master Quest (USA).rvz",
        "hash": "da950b045b49c392",
        "size": "938137012",
        "mtime": "1599532646"
    },
    {
        "dir": "Roms/Nintendo/Nintendo Gamecube/Legend of Zelda, The - The Wind Waker (USA)",
        "filename": "Legend of Zelda, The - The Wind Waker (USA).rvz",
        "hash": "fe09232421a83c32",
        "size": "882963284",
        "mtime": "1599532676"
    },
    {
        "dir": "Roms/Nintendo/Nintendo Gamecube/Legend of Zelda, The - Twilight Princess (USA)",
        "filename": "Legend of Zelda, The - Twilight Princess (USA).rvz",
        "hash": "749f3bd2158310a4",
        "size": "941670352",
        "mtime": "1599532704"
    },
    {
        "dir": "Roms/Nintendo/Nintendo Gamecube/Mega Man - Network Transmission (USA)",
        "filename": "Mega Man - Network Transmission (USA).rvz",
        "hash": "ad44806eaca4ff8a",
        "size": "482846560",
        "mtime": "1599530670"
    },
    {
        "dir": "Roms/Nintendo/Nintendo Gamecube/P.N. 03 (USA)",
        "filename": "P.N. 03 (USA).rvz",
        "hash": "5086adc693b49314",
        "size": "697345772",
        "mtime": "1599530762"
    },
    {
        "dir": "Roms/Nintendo/Nintendo Gamecube/Pac-Man Vs. (USA)",
        "filename": "Pac-Man Vs. (USA).rvz",
        "hash": "186bcaadfee6fd4a",
        "size": "52023320",
        "mtime": "1621554810"
    },
    {
        "dir": "Roms/Nintendo/Nintendo Gamecube/Paper Mario - The Thousand-Year Door (USA)",
        "filename": "Paper Mario - The Thousand-Year Door (USA).rvz",
        "hash": "dcf25f4708ffaa7b",
        "size": "351346148",
        "mtime": "1599530908"
    },
    {
        "dir": "Roms/Nintendo/Nintendo Gamecube/Phantasy Star Online Episode I & II (USA) (En,Ja,Fr,De,Es) (Rev 1)",
        "filename": "Phantasy Star Online Episode I & II (USA) (En,Ja,Fr,De,Es) (Rev 1).rvz",
        "hash": "d1e057a9a82407b5",
        "size": "1112454720",
        "mtime": "1599530948"
    },
    {
        "dir": "Roms/Nintendo/Nintendo Gamecube/Phantasy Star Online Episode III - C.A.R.D. Revolution (USA) (En,Ja)",
        "filename": "Phantasy Star Online Episode III - C.A.R.D. Revolution (USA) (En,Ja).rvz",
        "hash": "35ff3b8c80fb7601",
        "size": "1090560848",
        "mtime": "1599531008"
    },
    {
        "dir": "Roms/Nintendo/Nintendo Gamecube/Resident Evil (USA)",
        "filename": "Resident Evil (USA) (Disc 1).rvz",
        "hash": "7f69d44cc650927d",
        "size": "953431356",
        "mtime": "1599531307"
    },
    {
        "dir": "Roms/Nintendo/Nintendo Gamecube/Resident Evil (USA)",
        "filename": "Resident Evil (USA) (Disc 2).rvz",
        "hash": "6e7bf634b25d2f93",
        "size": "1109415304",
        "mtime": "1599531459"
    },
    {
        "dir": "Roms/Nintendo/Nintendo Gamecube/Resident Evil (USA)",
        "filename": "Resident Evil (USA).m3u",
        "hash": "cda6f70b43573faa",
        "size": "66",
        "mtime": "1599671466"
    },
    {
        "dir": "Roms/Nintendo/Nintendo Gamecube/Resident Evil - Code - Veronica X (USA)",
        "filename": "Resident Evil - Code - Veronica X (USA) (Disc 1).rvz",
        "hash": "63bfb93490f01e1e",
        "size": "902195048",
        "mtime": "1599531488"
    },
    {
        "dir": "Roms/Nintendo/Nintendo Gamecube/Resident Evil - Code - Veronica X (USA)",
        "filename": "Resident Evil - Code - Veronica X (USA) (Disc 2).rvz",
        "hash": "cd878a260f07ebce",
        "size": "1070922052",
        "mtime": "1599531520"
    },
    {
        "dir": "Roms/Nintendo/Nintendo Gamecube/Resident Evil - Code - Veronica X (USA)",
        "filename": "Resident Evil - Code - Veronica X (USA).m3u",
        "hash": "1495af287f7b8cab",
        "size": "106",
        "mtime": "1599671367"
    },
    {
        "dir": "Roms/Nintendo/Nintendo Gamecube/Resident Evil 2 (USA)",
        "filename": "Resident Evil 2 (USA).rvz",
        "hash": "d8457d34cc25d6e2",
        "size": "1161848876",
        "mtime": "1599531338"
    },
    {
        "dir": "Roms/Nintendo/Nintendo Gamecube/Resident Evil 3 - Nemesis (USA)",
        "filename": "Resident Evil 3 - Nemesis (USA).rvz",
        "hash": "6c8f66e36480f3db",
        "size": "806733964",
        "mtime": "1599531363"
    },
    {
        "dir": "Roms/Nintendo/Nintendo Gamecube/Resident Evil 4 (USA)",
        "filename": "Resident Evil 4 (USA) (Disc 1).rvz",
        "hash": "c8e580bde58af82f",
        "size": "1187013468",
        "mtime": "1599531399"
    },
    {
        "dir": "Roms/Nintendo/Nintendo Gamecube/Resident Evil 4 (USA)",
        "filename": "Resident Evil 4 (USA) (Disc 2).rvz",
        "hash": "ed3f503f7f85e498",
        "size": "1076588400",
        "mtime": "1599531428"
    },
    {
        "dir": "Roms/Nintendo/Nintendo Gamecube/Resident Evil 4 (USA)",
        "filename": "Resident Evil 4 (USA).m3u",
        "hash": "70b9876bdfe3a09c",
        "size": "70",
        "mtime": "1599671281"
    },
    {
        "dir": "Roms/Nintendo/Nintendo Gamecube/Resident Evil Zero (USA)",
        "filename": "Resident Evil Zero (USA) (Disc 1).rvz",
        "hash": "78802c80f1924a75",
        "size": "1257139980",
        "mtime": "1599531550"
    },
    {
        "dir": "Roms/Nintendo/Nintendo Gamecube/Resident Evil Zero (USA)",
        "filename": "Resident Evil Zero (USA) (Disc 2).rvz",
        "hash": "262fb0d5310fca86",
        "size": "1209395912",
        "mtime": "1599531579"
    },
    {
        "dir": "Roms/Nintendo/Nintendo Gamecube/Resident Evil Zero (USA)",
        "filename": "Resident Evil Zero (USA).m3u",
        "hash": "c1673041b5347ce7",
        "size": "76",
        "mtime": "1599671507"
    },
    {
        "dir": "Roms/Nintendo/Nintendo Gamecube/Shadow The Hedgehog (USA) (En,Ja,Fr,De,Es,It)",
        "filename": "Shadow The Hedgehog (USA) (En,Ja,Fr,De,Es,It).rvz",
        "hash": "247a959cb2099493",
        "size": "1171133920",
        "mtime": "1599531638"
    },
    {
        "dir": "Roms/Nintendo/Nintendo Gamecube/Skies of Arcadia Legends (USA)",
        "filename": "Skies of Arcadia Legends (USA).rvz",
        "hash": "7c3a7f2af0d8c7bb",
        "size": "1309912604",
        "mtime": "1599531668"
    },
    {
        "dir": "Roms/Nintendo/Nintendo Gamecube/Sonic Adventure 2 - Battle (USA) (En,Ja,Fr,De,Es)",
        "filename": "Sonic Adventure 2 - Battle (USA) (En,Ja,Fr,De,Es).rvz",
        "hash": "c48da194c93b0538",
        "size": "1171561024",
        "mtime": "1599531730"
    },
    {
        "dir": "Roms/Nintendo/Nintendo Gamecube/Sonic Adventure DX - Director's Cut (USA) (En,Ja,Fr,De,Es)",
        "filename": "Sonic Adventure DX - Director's Cut (USA) (En,Ja,Fr,De,Es).rvz",
        "hash": "f598a75727bb6ce7",
        "size": "1177066124",
        "mtime": "1599531759"
    },
    {
        "dir": "Roms/Nintendo/Nintendo Gamecube/Sonic Gems Collection (USA)",
        "filename": "Sonic Gems Collection (USA).rvz",
        "hash": "0c59f59de24f9569",
        "size": "1178428588",
        "mtime": "1599531790"
    },
    {
        "dir": "Roms/Nintendo/Nintendo Gamecube/Sonic Heroes (USA) (En,Ja,Fr,De,Es,It)",
        "filename": "Sonic Heroes (USA) (En,Ja,Fr,De,Es,It).rvz",
        "hash": "2d8f237bea318f2a",
        "size": "1023413500",
        "mtime": "1599531817"
    },
    {
        "dir": "Roms/Nintendo/Nintendo Gamecube/Sonic Riders (USA) (En,Ja,Fr,De,Es,It)",
        "filename": "Sonic Riders (USA) (En,Ja,Fr,De,Es,It).rvz",
        "hash": "6f59df6760cfdd2d",
        "size": "1252283304",
        "mtime": "1599531851"
    },
    {
        "dir": "Roms/Nintendo/Nintendo Gamecube/Soulcalibur II (USA)",
        "filename": "Soulcalibur II (USA).rvz",
        "hash": "73a2c6d52563ec05",
        "size": "805479888",
        "mtime": "1599531876"
    },
    {
        "dir": "Roms/Nintendo/Nintendo Gamecube/Super Mario Sunshine (USA)",
        "filename": "Super Mario Sunshine (USA).rvz",
        "hash": "f1ce73e7c40ceb62",
        "size": "1059921220",
        "mtime": "1622345426"
    },
    {
        "dir": "Roms/Nintendo/Nintendo Gamecube/Super Smash Bros. Melee (USA) (En,Ja) (Rev 1)",
        "filename": "Super Smash Bros. Melee (USA) (En,Ja) (Rev 1).rvz",
        "hash": "8c2f24288e4417b9",
        "size": "1166207876",
        "mtime": "1599532260"
    },
    {
        "dir": "Roms/Nintendo/Nintendo Gamecube/WarioWare, Inc. - Mega Party Games! (USA)",
        "filename": "WarioWare, Inc. - Mega Party Games! (USA).rvz",
        "hash": "ae05d0d2ca172472",
        "size": "675417296",
        "mtime": "1599533004"
    }
]