{
    "files": [
        "PowerWash Simulator (USA).7z.001",
        "PowerWash Simulator (USA).7z.002",
        "PowerWash Simulator (USA).exe"
    ],
    "installer_exe": [
        "SETUP_MAIN_ROOT/PowerWash Simulator (USA).exe"
    ],
    "main_game_exe": [
        "PowerWash Simulator/PowerWashSimulator.exe"
    ],
    "main_game_exe_cwd": {
        "PowerWash Simulator/PowerWashSimulator.exe": "PowerWash Simulator"
    },
    "steam": {
        "appid": "1290000",
        "branchid": "public",
        "builddate": "1722607664",
        "buildid": "14859577",
        "controller_support": "full",
        "installdir": "PowerWash Simulator",
        "keys": [],
        "name": "PowerWash Simulator",
        "paths": [
            "STORE_INSTALL_DIR/userdata/STORE_USER_ID/1290000",
            "USER_PROFILE_DIR/AppData/LocalLow/FuturLab/PowerWash Simulator"
        ]
    },
    "transform_file": "PowerWash Simulator (USA).exe"
}