{
    "files": [
        "Shadow Complex Remastered (USA).exe"
    ],
    "installer_exe": [
        "$SETUP_MAIN_ROOT/Shadow Complex Remastered (USA).exe"
    ],
    "main_game_exe": [
        "Shadow Complex Remastered/Binaries/Win32/ShadowComplexRemastered.exe"
    ],
    "main_game_exe_cwd": {
        "Shadow Complex Remastered/Binaries/Win32/ShadowComplexRemastered.exe": "Shadow Complex Remastered/Binaries/Win32"
    },
    "steam": {
        "appid": "385560",
        "branchid": "public",
        "controller_support": "full",
        "name": "Shadow Complex Remastered"
    },
    "transform_file": "Shadow Complex Remastered (USA).exe"
}