{
    "extra": [
        "soma_artwork.zip",
        "soma_wallpapers.zip"
    ],
    "files": [
        "extra/soma_artwork.zip",
        "extra/soma_wallpapers.zip",
        "setup_soma_1.61_(64bit)_(50360)-1.bin",
        "setup_soma_1.61_(64bit)_(50360)-2.bin",
        "setup_soma_1.61_(64bit)_(50360)-3.bin",
        "setup_soma_1.61_(64bit)_(50360).exe"
    ],
    "gog": {
        "appid": "1439487606",
        "appname": "soma",
        "appurl": "https://www.gog.com/en/game/soma",
        "buildid": "1.61",
        "keys": [],
        "name": "SOMA",
        "paths": []
    },
    "installer_exe": [
        "SETUP_MAIN_ROOT/setup_soma_1.61_(64bit)_(50360).exe"
    ],
    "main_game_exe": [
        "GOG Games/SOMA/Soma.exe"
    ],
    "main_game_exe_cwd": {
        "GOG Games/SOMA/Soma.exe": "GOG Games/SOMA"
    },
    "transform_file": "setup_soma_1.61_(64bit)_(50360).exe"
}