{
    "extra": [
        "ultima_8_chronicle.zip",
        "ultima_8_cluebook.zip",
        "ultima_8_lost_vale_design_documents.zip",
        "ultima_8_manual.zip",
        "ultima_8_map.zip",
        "ultima_8_reference_card.zip"
    ],
    "files": [
        "extra/ultima_8_chronicle.zip",
        "extra/ultima_8_cluebook.zip",
        "extra/ultima_8_lost_vale_design_documents.zip",
        "extra/ultima_8_manual.zip",
        "extra/ultima_8_map.zip",
        "extra/ultima_8_reference_card.zip",
        "setup_ultima_viii_-_pagan_1.0_cs_v2_(28831).exe"
    ],
    "gog": {
        "appid": "1207659015",
        "appname": "ultima_8_gold_edition",
        "appurl": "https://www.gog.com/en/game/ultima_8_gold_edition",
        "buildid": "1.0 CS v2",
        "keys": [],
        "name": "Ultima\u2122 8 Gold Edition",
        "paths": []
    },
    "transform_file": "setup_ultima_viii_-_pagan_1.0_cs_v2_(28831).exe"
}